LICENSE
MANIFEST.in
README.md
requirements.txt
setup.py
pyauto/__init__.py
pyauto.ouidb.egg-info/PKG-INFO
pyauto.ouidb.egg-info/SOURCES.txt
pyauto.ouidb.egg-info/dependency_links.txt
pyauto.ouidb.egg-info/requires.txt
pyauto.ouidb.egg-info/top_level.txt
pyauto/ouidb/__init__.py
pyauto/ouidb/api.py
pyauto/ouidb/commands.py
pyauto/ouidb/config.py
pyauto/ouidb/server.py