Metadata-Version: 1.0
Name: pyauto.ouidb
Version: 0.0.1
Summary: Builds a database from the OUI MAC vendors
Home-page: https://github.com/adamjaso/pyauto/tree/master/ouidb
Author: Adam Jaso
Author-email: UNKNOWN
License: GNU General Public License V2
Platform: UNKNOWN
